{
    "row": 0,
    "col": 0,
    "width": 10,
    "height": 10,
    "slotId": 0,
    "health": 1.0,
    "type": "SimpleStorageDefault",
    "quantity": 0.0,
    "isAmmo": 0,
    "ammo": 0,
    "flip": 0,
    "isFood": 0,
    "foodStage": 0,
    "attachments": [],
    "cargo": [
        {
            "row": 8,
            "col": 9,
            "width": 1,
            "height": 1,
            "slotId": 0,
            "health": 1.0,
            "type": "ZucchiniSeeds",
            "quantity": 19.0,
            "isAmmo": 0,
            "ammo": 0,
            "flip": 0,
            "isFood": 0,
            "foodStage": 0,
            "attachments": [],
            "cargo": []
        },
        {
            "row": 9,
            "col": 9,
            "width": 1,
            "height": 1,
            "slotId": 0,
            "health": 0.7786353826522827,
            "type": "Matchbox",
            "quantity": 85.0,
            "isAmmo": 0,
            "ammo": 0,
            "flip": 0,
            "isFood": 0,
            "foodStage": 0,
            "attachments": [],
            "cargo": []
        },
        {
            "row": 2,
            "col": 8,
            "width": 1,
            "height": 2,
            "slotId": 0,
            "health": 0.17999541759490968,
            "type": "TerjeAmpouleMetoclopramid",
            "quantity": 2.0,
            "isAmmo": 0,
            "ammo": 0,
            "flip": 0,
            "isFood": 0,
            "foodStage": 0,
            "attachments": [],
            "cargo": []
        },
        {
            "row": 0,
            "col": 0,
            "width": 2,
            "height": 3,
            "slotId": 0,
            "health": 0.17755398154258729,
            "type": "MetalWire",
            "quantity": 0.0,
            "isAmmo": 0,
            "ammo": 0,
            "flip": 0,
            "isFood": 0,
            "foodStage": 0,
            "attachments": [],
            "cargo": []
        },
        {
            "row": 2,
            "col": 9,
            "width": 1,
            "height": 2,
            "slotId": 0,
            "health": 0.1728389412164688,
            "type": "TerjeAmpouleNeirox",
            "quantity": 3.0,
            "isAmmo": 0,
            "ammo": 0,
            "flip": 0,
            "isFood": 0,
            "foodStage": 0,
            "attachments": [],
            "cargo": []
        },
        {
            "row": 7,
            "col": 0,
            "width": 1,
            "height": 3,
            "slotId": 0,
            "health": 1.0,
            "type": "Pliers",
            "quantity": 0.0,
            "isAmmo": 0,
            "ammo": 0,
            "flip": 0,
            "isFood": 0,
            "foodStage": 0,
            "attachments": [],
            "cargo": []
        },
        {
            "row": 0,
            "col": 9,
            "width": 1,
            "height": 2,
            "slotId": 0,
            "health": 0.9192798137664795,
            "type": "BandageDressing",
            "quantity": 4.0,
            "isAmmo": 0,
            "ammo": 0,
            "flip": 0,
            "isFood": 0,
            "foodStage": 0,
            "attachments": [],
            "cargo": []
        },
        {
            "row": 0,
            "col": 8,
            "width": 1,
            "height": 2,
            "slotId": 0,
            "health": 0.9554741382598877,
            "type": "BandageDressing",
            "quantity": 4.0,
            "isAmmo": 0,
            "ammo": 0,
            "flip": 0,
            "isFood": 0,
            "foodStage": 0,
            "attachments": [],
            "cargo": []
        },
        {
            "row": 3,
            "col": 1,
            "width": 1,
            "height": 2,
            "slotId": 0,
            "health": 0.19308766722679139,
            "type": "SewingKit",
            "quantity": 100.0,
            "isAmmo": 0,
            "ammo": 0,
            "flip": 0,
            "isFood": 0,
            "foodStage": 0,
            "attachments": [],
            "cargo": []
        },
        {
            "row": 0,
            "col": 6,
            "width": 1,
            "height": 2,
            "slotId": 0,
            "health": 0.1882505565881729,
            "type": "TerjeSurgicalTool_White",
            "quantity": 0.0,
            "isAmmo": 0,
            "ammo": 0,
            "flip": 0,
            "isFood": 0,
            "foodStage": 0,
            "attachments": [],
            "cargo": []
        },
        {
            "row": 0,
            "col": 5,
            "width": 1,
            "height": 2,
            "slotId": 0,
            "health": 0.3797818124294281,
            "type": "TerjeSurgicalTool_White",
            "quantity": 0.0,
            "isAmmo": 0,
            "ammo": 0,
            "flip": 0,
            "isFood": 0,
            "foodStage": 0,
            "attachments": [],
            "cargo": []
        },
        {
            "row": 0,
            "col": 4,
            "width": 1,
            "height": 2,
            "slotId": 0,
            "health": 0.3470664620399475,
            "type": "TerjeSurgicalTool_White",
            "quantity": 0.0,
            "isAmmo": 0,
            "ammo": 0,
            "flip": 0,
            "isFood": 0,
            "foodStage": 0,
            "attachments": [],
            "cargo": []
        },
        {
            "row": 2,
            "col": 5,
            "width": 1,
            "height": 2,
            "slotId": 0,
            "health": 0.8359349966049194,
            "type": "TerjeAmpouleGexobarbital",
            "quantity": 1.0,
            "isAmmo": 0,
            "ammo": 0,
            "flip": 0,
            "isFood": 0,
            "foodStage": 0,
            "attachments": [],
            "cargo": []
        },
        {
            "row": 3,
            "col": 0,
            "width": 1,
            "height": 2,
            "slotId": 0,
            "health": 1.0,
            "type": "RIP_WeaponCleaningSpray_2",
            "quantity": 50.0,
            "isAmmo": 0,
            "ammo": 0,
            "flip": 0,
            "isFood": 0,
            "foodStage": 0,
            "attachments": [],
            "cargo": []
        },
        {
            "row": 2,
            "col": 4,
            "width": 1,
            "height": 2,
            "slotId": 0,
            "health": 0.7125810384750366,
            "type": "TerjePillsParacetamol",
            "quantity": 10.0,
            "isAmmo": 0,
            "ammo": 0,
            "flip": 0,
            "isFood": 0,
            "foodStage": 0,
            "attachments": [],
            "cargo": []
        },
        {
            "row": 5,
            "col": 9,
            "width": 1,
            "height": 3,
            "slotId": 0,
            "health": 0.9969939589500427,
            "type": "Mag_AK74_30Rnd_Black",
            "quantity": 1.0,
            "isAmmo": 1,
            "ammo": 24,
            "flip": 0,
            "isFood": 0,
            "foodStage": 0,
            "attachments": [],
            "cargo": []
        },
        {
            "row": 3,
            "col": 2,
            "width": 1,
            "height": 2,
            "slotId": 0,
            "health": 0.9116807579994202,
            "type": "SewingKit",
            "quantity": 100.0,
            "isAmmo": 0,
            "ammo": 0,
            "flip": 0,
            "isFood": 0,
            "foodStage": 0,
            "attachments": [],
            "cargo": []
        },
        {
            "row": 5,
            "col": 0,
            "width": 2,
            "height": 1,
            "slotId": 0,
            "health": 0.2535744309425354,
            "type": "TireRepairKit",
            "quantity": 100.0,
            "isAmmo": 0,
            "ammo": 0,
            "flip": 1,
            "isFood": 0,
            "foodStage": 0,
            "attachments": [],
            "cargo": []
        },
        {
            "row": 5,
            "col": 1,
            "width": 1,
            "height": 2,
            "slotId": 0,
            "health": 0.9328450560569763,
            "type": "Whetstone",
            "quantity": 100.0,
            "isAmmo": 0,
            "ammo": 0,
            "flip": 0,
            "isFood": 0,
            "foodStage": 0,
            "attachments": [],
            "cargo": []
        }
    ]
}