<?xml version="1.0" encoding="UTF-8" standalone="yes"?>
<types>
	<type name="FB_Brown_b_bag">
		<nominal>0</nominal>
		<lifetime>14400</lifetime>
		<restock>0</restock>
		<min>0</min>
		<quantmin>-1</quantmin>
		<quantmax>-1</quantmax>
		<cost>100</cost>
		<flags count_in_cargo="0" count_in_hoarder="0" count_in_map="1" count_in_player="0" crafted="0" deloot="0" />
		<category name="clothes" />
	</type>
	<type name="FB_Jeans_b_green">
		<nominal>0</nominal>
		<lifetime>14400</lifetime>
		<restock>0</restock>
		<min>0</min>
		<quantmin>-1</quantmin>
		<quantmax>-1</quantmax>
		<cost>100</cost>
		<flags count_in_cargo="0" count_in_hoarder="0" count_in_map="1" count_in_player="0" crafted="0" deloot="0" />
		<category name="clothes" />
	</type>
	<type name="FB_Jeans_b_blue">
		<nominal>0</nominal>
		<lifetime>14400</lifetime>
		<restock>0</restock>
		<min>0</min>
		<quantmin>-1</quantmin>
		<quantmax>-1</quantmax>
		<cost>100</cost>
		<flags count_in_cargo="0" count_in_hoarder="0" count_in_map="1" count_in_player="0" crafted="0" deloot="0" />
		<category name="clothes" />
	</type>
	<type name="FB_Jeans">
		<nominal>0</nominal>
		<lifetime>14400</lifetime>
		<restock>0</restock>
		<min>0</min>
		<quantmin>-1</quantmin>
		<quantmax>-1</quantmax>
		<cost>100</cost>
		<flags count_in_cargo="0" count_in_hoarder="0" count_in_map="1" count_in_player="0" crafted="0" deloot="0" />
		<category name="clothes" />
	</type>
	<type name="FB_Jeans_b_red">
		<nominal>0</nominal>
		<lifetime>14400</lifetime>
		<restock>0</restock>
		<min>0</min>
		<quantmin>-1</quantmin>
		<quantmax>-1</quantmax>
		<cost>100</cost>
		<flags count_in_cargo="0" count_in_hoarder="0" count_in_map="1" count_in_player="0" crafted="0" deloot="0" />
		<category name="clothes" />
	</type>
	<type name="FB_Jeans_b_yellow">
		<nominal>0</nominal>
		<lifetime>14400</lifetime>
		<restock>0</restock>
		<min>0</min>
		<quantmin>-1</quantmin>
		<quantmax>-1</quantmax>
		<cost>100</cost>
		<flags count_in_cargo="0" count_in_hoarder="0" count_in_map="1" count_in_player="0" crafted="0" deloot="0" />
		<category name="clothes" />
	</type>
	<type name="FB_Burlap_bag">
		<nominal>0</nominal>
		<lifetime>14400</lifetime>
		<restock>0</restock>
		<min>0</min>
		<quantmin>-1</quantmin>
		<quantmax>-1</quantmax>
		<cost>100</cost>
		<flags count_in_cargo="0" count_in_hoarder="0" count_in_map="1" count_in_player="0" crafted="0" deloot="0" />
		<category name="clothes" />
	</type>
	<type name="FB_Fabric_bag">
		<nominal>0</nominal>
		<lifetime>14400</lifetime>
		<restock>0</restock>
		<min>0</min>
		<quantmin>-1</quantmin>
		<quantmax>-1</quantmax>
		<cost>100</cost>
		<flags count_in_cargo="0" count_in_hoarder="0" count_in_map="1" count_in_player="0" crafted="0" deloot="0" />
		<category name="clothes" />
	</type>
	<type name="FB_bandit_glowes_bronw">
		<nominal>10</nominal>
		<lifetime>14400</lifetime>
		<restock>0</restock>
		<min>10</min>
		<quantmin>-1</quantmin>
		<quantmax>-1</quantmax>
		<cost>100</cost>
		<flags count_in_cargo="0" count_in_hoarder="0" count_in_map="1" count_in_player="0" crafted="0" deloot="0" />
		<category name="clothes" />
		<usage name="Industrial" />
		<usage name="Farm" />
	</type>
	<type name="FB_bandit_gloves">
		<nominal>10</nominal>
		<lifetime>14400</lifetime>
		<restock>0</restock>
		<min>10</min>
		<quantmin>-1</quantmin>
		<quantmax>-1</quantmax>
		<cost>100</cost>
		<flags count_in_cargo="0" count_in_hoarder="0" count_in_map="1" count_in_player="0" crafted="0" deloot="0" />
		<category name="clothes" />
		<usage name="Industrial" />
		<usage name="Farm" />
	</type>
	<type name="FB_bandit_tan">
		<nominal>10</nominal>
		<lifetime>14400</lifetime>
		<restock>0</restock>
		<min>10</min>
		<quantmin>-1</quantmin>
		<quantmax>-1</quantmax>
		<cost>100</cost>
		<flags count_in_cargo="0" count_in_hoarder="0" count_in_map="1" count_in_player="0" crafted="0" deloot="0" />
		<category name="clothes" />
		<usage name="Industrial" />
		<usage name="Farm" />
	</type>
	<type name="FB_boxing_gloves_red">
		<nominal>15</nominal>
		<lifetime>14400</lifetime>
		<restock>0</restock>
		<min>10</min>
		<quantmin>-1</quantmin>
		<quantmax>-1</quantmax>
		<cost>100</cost>
		<flags count_in_cargo="0" count_in_hoarder="0" count_in_map="1" count_in_player="0" crafted="0" deloot="0" />
		<category name="clothes" />
		<usage name="Village" />
		<usage name="Town" />
	</type>
	<type name="FB_boxing_gloves_blue">
		<nominal>15</nominal>
		<lifetime>14400</lifetime>
		<restock>0</restock>
		<min>10</min>
		<quantmin>-1</quantmin>
		<quantmax>-1</quantmax>
		<cost>100</cost>
		<flags count_in_cargo="0" count_in_hoarder="0" count_in_map="1" count_in_player="0" crafted="0" deloot="0" />
		<category name="clothes" />
		<usage name="Village" />
		<usage name="Town" />
	</type>
	<type name="FB_half_gloves_grey">
		<nominal>0</nominal>
		<lifetime>14400</lifetime>
		<restock>0</restock>
		<min>0</min>
		<quantmin>-1</quantmin>
		<quantmax>-1</quantmax>
		<cost>100</cost>
		<flags count_in_cargo="0" count_in_hoarder="0" count_in_map="1" count_in_player="0" crafted="0" deloot="0" />
		<category name="clothes" />
	</type>
	<type name="FB_half_gloves_black">
		<nominal>0</nominal>
		<lifetime>14400</lifetime>
		<restock>0</restock>
		<min>0</min>
		<quantmin>-1</quantmin>
		<quantmax>-1</quantmax>
		<cost>100</cost>
		<flags count_in_cargo="0" count_in_hoarder="0" count_in_map="1" count_in_player="0" crafted="0" deloot="0" />
		<category name="clothes" />
	</type>
	<type name="FB_half_gloves_red">
		<nominal>0</nominal>
		<lifetime>14400</lifetime>
		<restock>0</restock>
		<min>0</min>
		<quantmin>-1</quantmin>
		<quantmax>-1</quantmax>
		<cost>100</cost>
		<flags count_in_cargo="0" count_in_hoarder="0" count_in_map="1" count_in_player="0" crafted="0" deloot="0" />
		<category name="clothes" />
	</type>
	<type name="FB_helmet_6b_47_cover_black">
		<nominal>0</nominal>
		<lifetime>14400</lifetime>
		<restock>0</restock>
		<min>0</min>
		<quantmin>-1</quantmin>
		<quantmax>-1</quantmax>
		<cost>100</cost>
		<flags count_in_cargo="0" count_in_hoarder="0" count_in_map="1" count_in_player="0" crafted="0" deloot="0" />
		<category name="clothes" />
	</type>
	<type name="FB_helmet_6b_47_cover_olive">
		<nominal>0</nominal>
		<lifetime>14400</lifetime>
		<restock>0</restock>
		<min>0</min>
		<quantmin>-1</quantmin>
		<quantmax>-1</quantmax>
		<cost>100</cost>
		<flags count_in_cargo="0" count_in_hoarder="0" count_in_map="1" count_in_player="0" crafted="0" deloot="0" />
		<category name="clothes" />
	</type>
	<type name="FB_Beanie_cap_2_red">
		<nominal>25</nominal>
		<lifetime>14400</lifetime>
		<restock>0</restock>
		<min>15</min>
		<quantmin>-1</quantmin>
		<quantmax>-1</quantmax>
		<cost>100</cost>
		<flags count_in_cargo="0" count_in_hoarder="0" count_in_map="1" count_in_player="0" crafted="0" deloot="0" />
		<category name="clothes" />
		<tag name="shelves" />
		<usage name="Town" />
	</type>
	<type name="FB_cowboy_hat_brown">
		<nominal>0</nominal>
		<lifetime>14400</lifetime>
		<restock>0</restock>
		<min>0</min>
		<quantmin>-1</quantmin>
		<quantmax>-1</quantmax>
		<cost>100</cost>
		<flags count_in_cargo="0" count_in_hoarder="0" count_in_map="1" count_in_player="0" crafted="0" deloot="0" />
		<category name="clothes" />
	</type>
	<type name="FB_fedora_brown">
		<nominal>30</nominal>
		<lifetime>14400</lifetime>
		<restock>0</restock>
		<min>15</min>
		<quantmin>-1</quantmin>
		<quantmax>-1</quantmax>
		<cost>100</cost>
		<flags count_in_cargo="0" count_in_hoarder="0" count_in_map="1" count_in_player="0" crafted="0" deloot="0" />
		<category name="clothes" />
		<tag name="shelves" />
		<usage name="Military" />
		<usage name="Hunting" />
		<usage name="Town"/>
		<usage name="Village"/>
	</type>
	<type name="FB_fedora_black">
		<nominal>30</nominal>
		<lifetime>14400</lifetime>
		<restock>0</restock>
		<min>15</min>
		<quantmin>-1</quantmin>
		<quantmax>-1</quantmax>
		<cost>100</cost>
		<flags count_in_cargo="0" count_in_hoarder="0" count_in_map="1" count_in_player="0" crafted="0" deloot="0" />
		<category name="clothes" />
		<tag name="shelves" />
		<usage name="Military" />
		<usage name="Hunting" />
		<usage name="Town"/>
		<usage name="Village"/>
	</type>
	<type name="FB_fedora_blue">
		<nominal>40</nominal>
		<lifetime>14400</lifetime>
		<restock>0</restock>
		<min>30</min>
		<quantmin>-1</quantmin>
		<quantmax>-1</quantmax>
		<cost>100</cost>
		<flags count_in_cargo="0" count_in_hoarder="0" count_in_map="1" count_in_player="0" crafted="0" deloot="0" />
		<category name="clothes" />
		<tag name="shelves" />
		<usage name="Town"/>
		<usage name="Village"/>
		<value name="Tier1" />
		<value name="Tier2" />
	</type>
	<type name="FB_cap_label_olive">
		<nominal>30</nominal>
		<lifetime>14400</lifetime>
		<restock>0</restock>
		<min>15</min>
		<quantmin>-1</quantmin>
		<quantmax>-1</quantmax>
		<cost>100</cost>
		<flags count_in_cargo="0" count_in_hoarder="0" count_in_map="1" count_in_player="0" crafted="0" deloot="0" />
		<category name="clothes" />
		<tag name="shelves" />
		<usage name="Town"/>
		<usage name="Village"/>
	</type>
	<type name="FB_cap_label_tan">
		<nominal>30</nominal>
		<lifetime>14400</lifetime>
		<restock>0</restock>
		<min>15</min>
		<quantmin>-1</quantmin>
		<quantmax>-1</quantmax>
		<cost>100</cost>
		<flags count_in_cargo="0" count_in_hoarder="0" count_in_map="1" count_in_player="0" crafted="0" deloot="0" />
		<category name="clothes" />
		<tag name="shelves" />
		<usage name="Town"/>
		<usage name="Village"/>
	</type>
	<type name="FB_cap_label_black">
		<nominal>30</nominal>
		<lifetime>14400</lifetime>
		<restock>0</restock>
		<min>15</min>
		<quantmin>-1</quantmin>
		<quantmax>-1</quantmax>
		<cost>100</cost>
		<flags count_in_cargo="0" count_in_hoarder="0" count_in_map="1" count_in_player="0" crafted="0" deloot="0" />
		<category name="clothes" />
		<tag name="shelves" />
		<usage name="Town"/>
		<usage name="Village"/>
	</type>
	<type name="FB_Safari_classic">
		<nominal>0</nominal>
		<lifetime>14400</lifetime>
		<restock>0</restock>
		<min>0</min>
		<quantmin>-1</quantmin>
		<quantmax>-1</quantmax>
		<cost>100</cost>
		<flags count_in_cargo="0" count_in_hoarder="0" count_in_map="1" count_in_player="0" crafted="0" deloot="0" />
		<category name="clothes" />
	</type>
	<type name="FB_ushanka_browm">
		<nominal>20</nominal>
		<lifetime>14400</lifetime>
		<restock>0</restock>
		<min>15</min>
		<quantmin>-1</quantmin>
		<quantmax>-1</quantmax>
		<cost>100</cost>
		<flags count_in_cargo="0" count_in_hoarder="0" count_in_map="1" count_in_player="0" crafted="0" deloot="0" />
		<category name="clothes" />
		<usage name="Village" />
	</type>
	<type name="FB_ushanka_black">
		<nominal>20</nominal>
		<lifetime>14400</lifetime>
		<restock>0</restock>
		<min>15</min>
		<quantmin>-1</quantmin>
		<quantmax>-1</quantmax>
		<cost>100</cost>
		<flags count_in_cargo="0" count_in_hoarder="0" count_in_map="1" count_in_player="0" crafted="0" deloot="0" />
		<category name="clothes" />
		<usage name="Village" />
	</type>
	<type name="FB_rasta">
		<nominal>0</nominal>
		<lifetime>14400</lifetime>
		<restock>0</restock>
		<min>0</min>
		<quantmin>-1</quantmin>
		<quantmax>-1</quantmax>
		<cost>100</cost>
		<flags count_in_cargo="0" count_in_hoarder="0" count_in_map="1" count_in_player="0" crafted="0" deloot="0" />
		<category name="clothes" />
	</type>
	<type name="FB_rasta_grey">
		<nominal>0</nominal>
		<lifetime>14400</lifetime>
		<restock>0</restock>
		<min>0</min>
		<quantmin>-1</quantmin>
		<quantmax>-1</quantmax>
		<cost>100</cost>
		<flags count_in_cargo="0" count_in_hoarder="0" count_in_map="1" count_in_player="0" crafted="0" deloot="0" />
		<category name="clothes" />
	</type>
	<type name="FB_rasta_green">
		<nominal>0</nominal>
		<lifetime>14400</lifetime>
		<restock>0</restock>
		<min>0</min>
		<quantmin>-1</quantmin>
		<quantmax>-1</quantmax>
		<cost>100</cost>
		<flags count_in_cargo="0" count_in_hoarder="0" count_in_map="1" count_in_player="0" crafted="0" deloot="0" />
		<category name="clothes" />
	</type>
	<type name="FB_rasta_brown">
		<nominal>0</nominal>
		<lifetime>14400</lifetime>
		<restock>0</restock>
		<min>0</min>
		<quantmin>-1</quantmin>
		<quantmax>-1</quantmax>
		<cost>100</cost>
		<flags count_in_cargo="0" count_in_hoarder="0" count_in_map="1" count_in_player="0" crafted="0" deloot="0" />
		<category name="clothes" />
	</type>
	<type name="FB_rasta_red">
		<nominal>0</nominal>
		<lifetime>14400</lifetime>
		<restock>0</restock>
		<min>0</min>
		<quantmin>-1</quantmin>
		<quantmax>-1</quantmax>
		<cost>100</cost>
		<flags count_in_cargo="0" count_in_hoarder="0" count_in_map="1" count_in_player="0" crafted="0" deloot="0" />
		<category name="clothes" />
	</type>
	<type name="FB_rasta_yellow">
		<nominal>0</nominal>
		<lifetime>14400</lifetime>
		<restock>0</restock>
		<min>0</min>
		<quantmin>-1</quantmin>
		<quantmax>-1</quantmax>
		<cost>100</cost>
		<flags count_in_cargo="0" count_in_hoarder="0" count_in_map="1" count_in_player="0" crafted="0" deloot="0" />
		<category name="clothes" />
	</type>
	<type name="FB_rasta_orange">
		<nominal>0</nominal>
		<lifetime>14400</lifetime>
		<restock>0</restock>
		<min>0</min>
		<quantmin>-1</quantmin>
		<quantmax>-1</quantmax>
		<cost>100</cost>
		<flags count_in_cargo="0" count_in_hoarder="0" count_in_map="1" count_in_player="0" crafted="0" deloot="0" />
		<category name="clothes" />
	</type>
	<type name="FB_ScreamMask">
		<nominal>0</nominal>
		<lifetime>14400</lifetime>
		<restock>0</restock>
		<min>0</min>
		<quantmin>-1</quantmin>
		<quantmax>-1</quantmax>
		<cost>100</cost>
		<flags count_in_cargo="0" count_in_hoarder="0" count_in_map="1" count_in_player="0" crafted="0" deloot="0" />
		<category name="clothes" />
	</type>
	<type name="FB_sphera_helmet_olive">
		<nominal>0</nominal>
		<lifetime>14400</lifetime>
		<restock>0</restock>
		<min>0</min>
		<quantmin>-1</quantmin>
		<quantmax>-1</quantmax>
		<cost>100</cost>
		<flags count_in_cargo="0" count_in_hoarder="0" count_in_map="1" count_in_player="0" crafted="0" deloot="0" />
		<category name="clothes" />
	</type>
	<type name="FB_sphera_black">
		<nominal>0</nominal>
		<lifetime>14400</lifetime>
		<restock>0</restock>
		<min>0</min>
		<quantmin>-1</quantmin>
		<quantmax>-1</quantmax>
		<cost>100</cost>
		<flags count_in_cargo="0" count_in_hoarder="0" count_in_map="1" count_in_player="0" crafted="0" deloot="0" />
		<category name="clothes" />
	</type>
	<type name="FB_ushanka2_black">
		<nominal>0</nominal>
		<lifetime>14400</lifetime>
		<restock>0</restock>
		<min>0</min>
		<quantmin>-1</quantmin>
		<quantmax>-1</quantmax>
		<cost>100</cost>
		<flags count_in_cargo="0" count_in_hoarder="0" count_in_map="1" count_in_player="0" crafted="0" deloot="0" />
		<category name="clothes" />
	</type>
	<type name="FB_Knife_homemade">
		<nominal>0</nominal>
		<lifetime>14400</lifetime>
		<restock>0</restock>
		<min>0</min>
		<quantmin>-1</quantmin>
		<quantmax>-1</quantmax>
		<cost>100</cost>
		<flags count_in_cargo="0" count_in_hoarder="0" count_in_map="1" count_in_player="0" crafted="0" deloot="0" />
		<category name="clothes" />
	</type>
	<type name="FB_gorka_pants_g">
		<nominal>0</nominal>
		<lifetime>14400</lifetime>
		<restock>0</restock>
		<min>0</min>
		<quantmin>-1</quantmin>
		<quantmax>-1</quantmax>
		<cost>100</cost>
		<flags count_in_cargo="0" count_in_hoarder="0" count_in_map="1" count_in_player="0" crafted="0" deloot="0" />
		<category name="clothes" />
	</type>
	<type name="FB_gorka_pants_t">
		<nominal>0</nominal>
		<lifetime>14400</lifetime>
		<restock>0</restock>
		<min>0</min>
		<quantmin>-1</quantmin>
		<quantmax>-1</quantmax>
		<cost>100</cost>
		<flags count_in_cargo="0" count_in_hoarder="0" count_in_map="1" count_in_player="0" crafted="0" deloot="0" />
		<category name="clothes" />
	</type>
	<type name="FB_gorka_pants">
		<nominal>0</nominal>
		<lifetime>14400</lifetime>
		<restock>0</restock>
		<min>0</min>
		<quantmin>-1</quantmin>
		<quantmax>-1</quantmax>
		<cost>100</cost>
		<flags count_in_cargo="0" count_in_hoarder="0" count_in_map="1" count_in_player="0" crafted="0" deloot="0" />
		<category name="clothes" />
	</type>
	<type name="FB_stalker_pants">
		<nominal>0</nominal>
		<lifetime>14400</lifetime>
		<restock>0</restock>
		<min>0</min>
		<quantmin>-1</quantmin>
		<quantmax>-1</quantmax>
		<cost>100</cost>
		<flags count_in_cargo="0" count_in_hoarder="0" count_in_map="1" count_in_player="0" crafted="0" deloot="0" />
		<category name="clothes" />
	</type>
	<type name="FB_tactical_pants">
		<nominal>0</nominal>
		<lifetime>14400</lifetime>
		<restock>0</restock>
		<min>0</min>
		<quantmin>-1</quantmin>
		<quantmax>-1</quantmax>
		<cost>100</cost>
		<flags count_in_cargo="0" count_in_hoarder="0" count_in_map="1" count_in_player="0" crafted="0" deloot="0" />
		<category name="clothes" />
	</type>
	<type name="FB_tactical_pants_green">
		<nominal>0</nominal>
		<lifetime>14400</lifetime>
		<restock>0</restock>
		<min>0</min>
		<quantmin>-1</quantmin>
		<quantmax>-1</quantmax>
		<cost>100</cost>
		<flags count_in_cargo="0" count_in_hoarder="0" count_in_map="1" count_in_player="0" crafted="0" deloot="0" />
		<category name="clothes" />
	</type>
	<type name="FB_tactical_pants_leather">
		<nominal>0</nominal>
		<lifetime>14400</lifetime>
		<restock>0</restock>
		<min>0</min>
		<quantmin>-1</quantmin>
		<quantmax>-1</quantmax>
		<cost>100</cost>
		<flags count_in_cargo="0" count_in_hoarder="0" count_in_map="1" count_in_player="0" crafted="0" deloot="0" />
		<category name="clothes" />
	</type>
	<type name="FB_tactical_pants_pixel">
		<nominal>0</nominal>
		<lifetime>14400</lifetime>
		<restock>0</restock>
		<min>0</min>
		<quantmin>-1</quantmin>
		<quantmax>-1</quantmax>
		<cost>100</cost>
		<flags count_in_cargo="0" count_in_hoarder="0" count_in_map="1" count_in_player="0" crafted="0" deloot="0" />
		<category name="clothes" />
	</type>
	<type name="FB_tactical_pants_grey">
		<nominal>0</nominal>
		<lifetime>14400</lifetime>
		<restock>0</restock>
		<min>0</min>
		<quantmin>-1</quantmin>
		<quantmax>-1</quantmax>
		<cost>100</cost>
		<flags count_in_cargo="0" count_in_hoarder="0" count_in_map="1" count_in_player="0" crafted="0" deloot="0" />
		<category name="clothes" />
	</type>
	<type name="FB_tactical_pants_blue">
		<nominal>0</nominal>
		<lifetime>14400</lifetime>
		<restock>0</restock>
		<min>0</min>
		<quantmin>-1</quantmin>
		<quantmax>-1</quantmax>
		<cost>100</cost>
		<flags count_in_cargo="0" count_in_hoarder="0" count_in_map="1" count_in_player="0" crafted="0" deloot="0" />
		<category name="clothes" />
	</type>
	<type name="FB_tactical_pants_black">
		<nominal>0</nominal>
		<lifetime>14400</lifetime>
		<restock>0</restock>
		<min>0</min>
		<quantmin>-1</quantmin>
		<quantmax>-1</quantmax>
		<cost>100</cost>
		<flags count_in_cargo="0" count_in_hoarder="0" count_in_map="1" count_in_player="0" crafted="0" deloot="0" />
		<category name="clothes" />
	</type>
	<type name="FB_tactical_pants_tan">
		<nominal>0</nominal>
		<lifetime>14400</lifetime>
		<restock>0</restock>
		<min>0</min>
		<quantmin>-1</quantmin>
		<quantmax>-1</quantmax>
		<cost>100</cost>
		<flags count_in_cargo="0" count_in_hoarder="0" count_in_map="1" count_in_player="0" crafted="0" deloot="0" />
		<category name="clothes" />
	</type>
	<type name="FB_tactical_pants_ADM">
		<nominal>0</nominal>
		<lifetime>14400</lifetime>
		<restock>0</restock>
		<min>0</min>
		<quantmin>-1</quantmin>
		<quantmax>-1</quantmax>
		<cost>100</cost>
		<flags count_in_cargo="0" count_in_hoarder="0" count_in_map="1" count_in_player="0" crafted="0" deloot="0" />
		<category name="clothes" />
	</type>
	<type name="FB_vatnik_pant_shirt_brown">
		<nominal>0</nominal>
		<lifetime>14400</lifetime>
		<restock>0</restock>
		<min>0</min>
		<quantmin>-1</quantmin>
		<quantmax>-1</quantmax>
		<cost>100</cost>
		<flags count_in_cargo="0" count_in_hoarder="0" count_in_map="1" count_in_player="0" crafted="0" deloot="0" />
		<category name="clothes" />
	</type>
	<type name="FB_vatnik_pant_long_brown">
		<nominal>0</nominal>
		<lifetime>14400</lifetime>
		<restock>0</restock>
		<min>0</min>
		<quantmin>-1</quantmin>
		<quantmax>-1</quantmax>
		<cost>100</cost>
		<flags count_in_cargo="0" count_in_hoarder="0" count_in_map="1" count_in_player="0" crafted="0" deloot="0" />
		<category name="clothes" />
	</type>
	<type name="FB_galoshi_black">
		<nominal>110</nominal>
		<lifetime>14400</lifetime>
		<restock>0</restock>
		<min>70</min>
		<quantmin>-1</quantmin>
		<quantmax>-1</quantmax>
		<cost>100</cost>
		<flags count_in_cargo="0" count_in_hoarder="0" count_in_map="1" count_in_player="0" crafted="0" deloot="0" />
		<category name="clothes" />
		<tag name="floor" />
		<usage name="Industrial" />
		<usage name="Farm" />
		<usage name="Village" />
	</type>
	<type name="FB_reebak_pink">
		<nominal>0</nominal>
		<lifetime>14400</lifetime>
		<restock>0</restock>
		<min>0</min>
		<quantmin>-1</quantmin>
		<quantmax>-1</quantmax>
		<cost>100</cost>
		<flags count_in_cargo="0" count_in_hoarder="0" count_in_map="1" count_in_player="0" crafted="0" deloot="0" />
		<category name="clothes" />
		<tag name="floor" />
		<usage name="Town" />
		<usage name="School" />
	</type>
	<type name="FB_rebak_original">
		<nominal>30</nominal>
		<lifetime>14400</lifetime>
		<restock>0</restock>
		<min>25</min>
		<quantmin>-1</quantmin>
		<quantmax>-1</quantmax>
		<cost>100</cost>
		<flags count_in_cargo="0" count_in_hoarder="0" count_in_map="1" count_in_player="0" crafted="0" deloot="0" />
		<category name="clothes" />
		<tag name="floor" />
		<usage name="Town" />
		<usage name="School" />
	</type>
	<type name="FB_rebak_purple">
		<nominal>30</nominal>
		<lifetime>14400</lifetime>
		<restock>0</restock>
		<min>25</min>
		<quantmin>-1</quantmin>
		<quantmax>-1</quantmax>
		<cost>100</cost>
		<flags count_in_cargo="0" count_in_hoarder="0" count_in_map="1" count_in_player="0" crafted="0" deloot="0" />
		<category name="clothes" />
		<tag name="floor" />
		<usage name="Town" />
		<usage name="School" />
	</type>
	<type name="FB_rebak_green">
		<nominal>30</nominal>
		<lifetime>14400</lifetime>
		<restock>0</restock>
		<min>25</min>
		<quantmin>-1</quantmin>
		<quantmax>-1</quantmax>
		<cost>100</cost>
		<flags count_in_cargo="0" count_in_hoarder="0" count_in_map="1" count_in_player="0" crafted="0" deloot="0" />
		<category name="clothes" />
		<tag name="floor" />
		<usage name="Town" />
		<usage name="School" />
	</type>
	<type name="FB_rebak_mint">
		<nominal>30</nominal>
		<lifetime>14400</lifetime>
		<restock>0</restock>
		<min>25</min>
		<quantmin>-1</quantmin>
		<quantmax>-1</quantmax>
		<cost>100</cost>
		<flags count_in_cargo="0" count_in_hoarder="0" count_in_map="1" count_in_player="0" crafted="0" deloot="0" />
		<category name="clothes" />
		<tag name="floor" />
		<usage name="Town" />
		<usage name="School" />
	</type>
	<type name="FB_rebak_white">
		<nominal>30</nominal>
		<lifetime>14400</lifetime>
		<restock>0</restock>
		<min>25</min>
		<quantmin>-1</quantmin>
		<quantmax>-1</quantmax>
		<cost>100</cost>
		<flags count_in_cargo="0" count_in_hoarder="0" count_in_map="1" count_in_player="0" crafted="0" deloot="0" />
		<category name="clothes" />
		<tag name="floor" />
		<usage name="Town" />
		<usage name="School" />
	</type>
	<type name="FB_rebak_pink">
		<nominal>30</nominal>
		<lifetime>14400</lifetime>
		<restock>0</restock>
		<min>25</min>
		<quantmin>-1</quantmin>
		<quantmax>-1</quantmax>
		<cost>100</cost>
		<flags count_in_cargo="0" count_in_hoarder="0" count_in_map="1" count_in_player="0" crafted="0" deloot="0" />
		<category name="clothes" />
		<tag name="floor" />
		<usage name="Town" />
		<usage name="School" />
	</type>
	<type name="FB_rebak_blue">
		<nominal>30</nominal>
		<lifetime>14400</lifetime>
		<restock>0</restock>
		<min>25</min>
		<quantmin>-1</quantmin>
		<quantmax>-1</quantmax>
		<cost>100</cost>
		<flags count_in_cargo="0" count_in_hoarder="0" count_in_map="1" count_in_player="0" crafted="0" deloot="0" />
		<category name="clothes" />
		<tag name="floor" />
		<usage name="Town" />
		<usage name="School" />
	</type>
	<type name="FB_rebak_purp_orng">
		<nominal>30</nominal>
		<lifetime>14400</lifetime>
		<restock>0</restock>
		<min>25</min>
		<quantmin>-1</quantmin>
		<quantmax>-1</quantmax>
		<cost>100</cost>
		<flags count_in_cargo="0" count_in_hoarder="0" count_in_map="1" count_in_player="0" crafted="0" deloot="0" />
		<category name="clothes" />
		<tag name="floor" />
		<usage name="Town" />
		<usage name="School" />
	</type>
	<type name="FB_rebak2_new">
		<nominal>2</nominal>
		<lifetime>14400</lifetime>
		<restock>0</restock>
		<min>1</min>
		<quantmin>-1</quantmin>
		<quantmax>-1</quantmax>
		<cost>100</cost>
		<flags count_in_cargo="0" count_in_hoarder="0" count_in_map="1" count_in_player="0" crafted="0" deloot="0" />
		<category name="clothes" />
		<tag name="floor" />
		<usage name="Town" />
		<usage name="School" />
	</type>
	<type name="FB_shoes_3_red">
		<nominal>20</nominal>
		<lifetime>14400</lifetime>
		<restock>0</restock>
		<min>10</min>
		<quantmin>-1</quantmin>
		<quantmax>-1</quantmax>
		<cost>100</cost>
		<flags count_in_cargo="0" count_in_hoarder="0" count_in_map="1" count_in_player="0" crafted="0" deloot="0" />
		<category name="clothes" />
		<tag name="floor" />
		<usage name="Town" />
		<usage name="Village" />
	</type>
	<type name="FB_shoes_3_black">
		<nominal>20</nominal>
		<lifetime>14400</lifetime>
		<restock>0</restock>
		<min>10</min>
		<quantmin>-1</quantmin>
		<quantmax>-1</quantmax>
		<cost>100</cost>
		<flags count_in_cargo="0" count_in_hoarder="0" count_in_map="1" count_in_player="0" crafted="0" deloot="0" />
		<category name="clothes" />
		<tag name="floor" />
		<usage name="Town" />
		<usage name="Village" />
	</type>
	<type name="FB_shoes_3_grey">
		<nominal>20</nominal>
		<lifetime>14400</lifetime>
		<restock>0</restock>
		<min>10</min>
		<quantmin>-1</quantmin>
		<quantmax>-1</quantmax>
		<cost>100</cost>
		<flags count_in_cargo="0" count_in_hoarder="0" count_in_map="1" count_in_player="0" crafted="0" deloot="0" />
		<category name="clothes" />
		<tag name="floor" />
		<usage name="Town" />
		<usage name="Village" />
	</type>
	<type name="FB_tapki_grey">
		<nominal>0</nominal>
		<lifetime>14400</lifetime>
		<restock>0</restock>
		<min>0</min>
		<quantmin>-1</quantmin>
		<quantmax>-1</quantmax>
		<cost>100</cost>
		<flags count_in_cargo="0" count_in_hoarder="0" count_in_map="1" count_in_player="0" crafted="0" deloot="0" />
		<category name="clothes" />
	</type>
	<type name="FB_tapki_red">
		<nominal>0</nominal>
		<lifetime>14400</lifetime>
		<restock>0</restock>
		<min>0</min>
		<quantmin>-1</quantmin>
		<quantmax>-1</quantmax>
		<cost>100</cost>
		<flags count_in_cargo="0" count_in_hoarder="0" count_in_map="1" count_in_player="0" crafted="0" deloot="0" />
		<category name="clothes" />
	</type>
	<type name="FB_tapki_brown">
		<nominal>0</nominal>
		<lifetime>14400</lifetime>
		<restock>0</restock>
		<min>0</min>
		<quantmin>-1</quantmin>
		<quantmax>-1</quantmax>
		<cost>100</cost>
		<flags count_in_cargo="0" count_in_hoarder="0" count_in_map="1" count_in_player="0" crafted="0" deloot="0" />
		<category name="clothes" />
	</type>
	<type name="FB_tapki_blue">
		<nominal>0</nominal>
		<lifetime>14400</lifetime>
		<restock>0</restock>
		<min>0</min>
		<quantmin>-1</quantmin>
		<quantmax>-1</quantmax>
		<cost>100</cost>
		<flags count_in_cargo="0" count_in_hoarder="0" count_in_map="1" count_in_player="0" crafted="0" deloot="0" />
		<category name="clothes" />
	</type>
	<type name="FB_tapki_green">
		<nominal>0</nominal>
		<lifetime>14400</lifetime>
		<restock>0</restock>
		<min>0</min>
		<quantmin>-1</quantmin>
		<quantmax>-1</quantmax>
		<cost>100</cost>
		<flags count_in_cargo="0" count_in_hoarder="0" count_in_map="1" count_in_player="0" crafted="0" deloot="0" />
		<category name="clothes" />
	</type>
	<type name="FB_tapki_kletka_green">
		<nominal>15</nominal>
		<lifetime>14400</lifetime>
		<restock>0</restock>
		<min>10</min>
		<quantmin>-1</quantmin>
		<quantmax>-1</quantmax>
		<cost>100</cost>
		<flags count_in_cargo="0" count_in_hoarder="0" count_in_map="1" count_in_player="0" crafted="0" deloot="0" />
		<category name="clothes" />
		<usage name="Town"/>
		<usage name="Village"/>
	</type>
	<type name="FB_tapki_kletka_Red">
		<nominal>15</nominal>
		<lifetime>14400</lifetime>
		<restock>0</restock>
		<min>10</min>
		<quantmin>-1</quantmin>
		<quantmax>-1</quantmax>
		<cost>100</cost>
		<flags count_in_cargo="0" count_in_hoarder="0" count_in_map="1" count_in_player="0" crafted="0" deloot="0" />
		<category name="clothes" />
		<usage name="Town"/>
		<usage name="Village"/>
	</type>
	<type name="FB_tapki_kletka_yellow">
		<nominal>15</nominal>
		<lifetime>14400</lifetime>
		<restock>0</restock>
		<min>10</min>
		<quantmin>-1</quantmin>
		<quantmax>-1</quantmax>
		<cost>100</cost>
		<flags count_in_cargo="0" count_in_hoarder="0" count_in_map="1" count_in_player="0" crafted="0" deloot="0" />
		<category name="clothes" />
	</type>
	<type name="FB_tapki_kletka_stich_yellow">
		<nominal>15</nominal>
		<lifetime>14400</lifetime>
		<restock>0</restock>
		<min>10</min>
		<quantmin>-1</quantmin>
		<quantmax>-1</quantmax>
		<cost>100</cost>
		<flags count_in_cargo="0" count_in_hoarder="0" count_in_map="1" count_in_player="0" crafted="0" deloot="0" />
		<category name="clothes" />
		<usage name="Town"/>
		<usage name="Village"/>
	</type>
	<type name="FB_tapki_kletka_stich_green">
		<nominal>15</nominal>
		<lifetime>14400</lifetime>
		<restock>0</restock>
		<min>10</min>
		<quantmin>-1</quantmin>
		<quantmax>-1</quantmax>
		<cost>100</cost>
		<flags count_in_cargo="0" count_in_hoarder="0" count_in_map="1" count_in_player="0" crafted="0" deloot="0" />
		<category name="clothes" />
	</type>
	<type name="FB_tapki_kletka_stich_Red">
		<nominal>15</nominal>
		<lifetime>14400</lifetime>
		<restock>0</restock>
		<min>10</min>
		<quantmin>-1</quantmin>
		<quantmax>-1</quantmax>
		<cost>100</cost>
		<flags count_in_cargo="0" count_in_hoarder="0" count_in_map="1" count_in_player="0" crafted="0" deloot="0" />
		<category name="clothes" />
		<usage name="Town"/>
		<usage name="Village"/>
	</type>
	<type name="FB_winter_boots_pink">
		<nominal>20</nominal>
		<lifetime>14400</lifetime>
		<restock>0</restock>
		<min>10</min>
		<quantmin>-1</quantmin>
		<quantmax>-1</quantmax>
		<cost>100</cost>
		<flags count_in_cargo="0" count_in_hoarder="0" count_in_map="1" count_in_player="0" crafted="0" deloot="0" />
		<category name="clothes" />
		<tag name="floor" />
		<usage name="Town" />
		<usage name="Village" />
	</type>
	<type name="FB_winter_boots_black">
		<nominal>20</nominal>
		<lifetime>14400</lifetime>
		<restock>0</restock>
		<min>10</min>
		<quantmin>-1</quantmin>
		<quantmax>-1</quantmax>
		<cost>100</cost>
		<flags count_in_cargo="0" count_in_hoarder="0" count_in_map="1" count_in_player="0" crafted="0" deloot="0" />
		<category name="clothes" />
		<tag name="floor" />
		<usage name="Town" />
		<usage name="Village" />
	</type>
	<type name="FB_winter_boots_blue">
		<nominal>0</nominal>
		<lifetime>14400</lifetime>
		<restock>0</restock>
		<min>0</min>
		<quantmin>-1</quantmin>
		<quantmax>-1</quantmax>
		<cost>100</cost>
		<flags count_in_cargo="0" count_in_hoarder="0" count_in_map="1" count_in_player="0" crafted="0" deloot="0" />
		<category name="clothes" />
	</type>
	<type name="FB_winter_boots_brown">
		<nominal>0</nominal>
		<lifetime>14400</lifetime>
		<restock>0</restock>
		<min>0</min>
		<quantmin>-1</quantmin>
		<quantmax>-1</quantmax>
		<cost>100</cost>
		<flags count_in_cargo="0" count_in_hoarder="0" count_in_map="1" count_in_player="0" crafted="0" deloot="0" />
		<category name="clothes" />
	</type>
	<type name="FB_winter_boots_green">
		<nominal>0</nominal>
		<lifetime>14400</lifetime>
		<restock>0</restock>
		<min>0</min>
		<quantmin>-1</quantmin>
		<quantmax>-1</quantmax>
		<cost>100</cost>
		<flags count_in_cargo="0" count_in_hoarder="0" count_in_map="1" count_in_player="0" crafted="0" deloot="0" />
		<category name="clothes" />
	</type>
	<type name="FB_winter_boots_olive">
		<nominal>0</nominal>
		<lifetime>14400</lifetime>
		<restock>0</restock>
		<min>0</min>
		<quantmin>-1</quantmin>
		<quantmax>-1</quantmax>
		<cost>100</cost>
		<flags count_in_cargo="0" count_in_hoarder="0" count_in_map="1" count_in_player="0" crafted="0" deloot="0" />
		<category name="clothes" />
	</type>
	<type name="FB_winter_boots_purple">
		<nominal>0</nominal>
		<lifetime>14400</lifetime>
		<restock>0</restock>
		<min>0</min>
		<quantmin>-1</quantmin>
		<quantmax>-1</quantmax>
		<cost>100</cost>
		<flags count_in_cargo="0" count_in_hoarder="0" count_in_map="1" count_in_player="0" crafted="0" deloot="0" />
		<category name="clothes" />
	</type>
	<type name="FB_winter_boots_red">
		<nominal>0</nominal>
		<lifetime>14400</lifetime>
		<restock>0</restock>
		<min>0</min>
		<quantmin>-1</quantmin>
		<quantmax>-1</quantmax>
		<cost>100</cost>
		<flags count_in_cargo="0" count_in_hoarder="0" count_in_map="1" count_in_player="0" crafted="0" deloot="0" />
		<category name="clothes" />
	</type>
	<type name="FB_SG_Mask_krug">
		<nominal>0</nominal>
		<lifetime>14400</lifetime>
		<restock>0</restock>
		<min>0</min>
		<quantmin>-1</quantmin>
		<quantmax>-1</quantmax>
		<cost>100</cost>
		<flags count_in_cargo="0" count_in_hoarder="0" count_in_map="1" count_in_player="0" crafted="0" deloot="0" />
		<category name="clothes" />
	</type>
	<type name="FB_SG_Mask_kvadrat">
		<nominal>0</nominal>
		<lifetime>14400</lifetime>
		<restock>0</restock>
		<min>0</min>
		<quantmin>-1</quantmin>
		<quantmax>-1</quantmax>
		<cost>100</cost>
		<flags count_in_cargo="0" count_in_hoarder="0" count_in_map="1" count_in_player="0" crafted="0" deloot="0" />
		<category name="clothes" />
	</type>
	<type name="FB_SG_Mask_treugol">
		<nominal>0</nominal>
		<lifetime>14400</lifetime>
		<restock>0</restock>
		<min>0</min>
		<quantmin>-1</quantmin>
		<quantmax>-1</quantmax>
		<cost>100</cost>
		<flags count_in_cargo="0" count_in_hoarder="0" count_in_map="1" count_in_player="0" crafted="0" deloot="0" />
		<category name="clothes" />
	</type>
	<type name="FB_SG_Hood">
		<nominal>0</nominal>
		<lifetime>14400</lifetime>
		<restock>0</restock>
		<min>0</min>
		<quantmin>-1</quantmin>
		<quantmax>-1</quantmax>
		<cost>100</cost>
		<flags count_in_cargo="0" count_in_hoarder="0" count_in_map="1" count_in_player="0" crafted="0" deloot="0" />
		<category name="clothes" />
	</type>
	<type name="FB_SG_Hood_pixel">
		<nominal>0</nominal>
		<lifetime>14400</lifetime>
		<restock>0</restock>
		<min>0</min>
		<quantmin>-1</quantmin>
		<quantmax>-1</quantmax>
		<cost>100</cost>
		<flags count_in_cargo="0" count_in_hoarder="0" count_in_map="1" count_in_player="0" crafted="0" deloot="0" />
		<category name="clothes" />
	</type>
	<type name="FB_SG_Hood_black">
		<nominal>0</nominal>
		<lifetime>14400</lifetime>
		<restock>0</restock>
		<min>0</min>
		<quantmin>-1</quantmin>
		<quantmax>-1</quantmax>
		<cost>100</cost>
		<flags count_in_cargo="0" count_in_hoarder="0" count_in_map="1" count_in_player="0" crafted="0" deloot="0" />
		<category name="clothes" />
	</type>
	<type name="FB_SG_Hood_green">
		<nominal>0</nominal>
		<lifetime>14400</lifetime>
		<restock>0</restock>
		<min>0</min>
		<quantmin>-1</quantmin>
		<quantmax>-1</quantmax>
		<cost>100</cost>
		<flags count_in_cargo="0" count_in_hoarder="0" count_in_map="1" count_in_player="0" crafted="0" deloot="0" />
		<category name="clothes" />
	</type>
	<type name="FB_SG_Pants">
		<nominal>0</nominal>
		<lifetime>14400</lifetime>
		<restock>0</restock>
		<min>0</min>
		<quantmin>-1</quantmin>
		<quantmax>-1</quantmax>
		<cost>100</cost>
		<flags count_in_cargo="0" count_in_hoarder="0" count_in_map="1" count_in_player="0" crafted="0" deloot="0" />
		<category name="clothes" />
	</type>
	<type name="FB_SG_Pants_pixel">
		<nominal>0</nominal>
		<lifetime>14400</lifetime>
		<restock>0</restock>
		<min>0</min>
		<quantmin>-1</quantmin>
		<quantmax>-1</quantmax>
		<cost>100</cost>
		<flags count_in_cargo="0" count_in_hoarder="0" count_in_map="1" count_in_player="0" crafted="0" deloot="0" />
		<category name="clothes" />
	</type>
	<type name="FB_SG_Pants_black">
		<nominal>0</nominal>
		<lifetime>14400</lifetime>
		<restock>0</restock>
		<min>0</min>
		<quantmin>-1</quantmin>
		<quantmax>-1</quantmax>
		<cost>100</cost>
		<flags count_in_cargo="0" count_in_hoarder="0" count_in_map="1" count_in_player="0" crafted="0" deloot="0" />
		<category name="clothes" />
	</type>
	<type name="FB_SG_Pants_green">
		<nominal>0</nominal>
		<lifetime>14400</lifetime>
		<restock>0</restock>
		<min>0</min>
		<quantmin>-1</quantmin>
		<quantmax>-1</quantmax>
		<cost>100</cost>
		<flags count_in_cargo="0" count_in_hoarder="0" count_in_map="1" count_in_player="0" crafted="0" deloot="0" />
		<category name="clothes" />
	</type>
	<type name="FB_SG_Jacket">
		<nominal>0</nominal>
		<lifetime>14400</lifetime>
		<restock>0</restock>
		<min>0</min>
		<quantmin>-1</quantmin>
		<quantmax>-1</quantmax>
		<cost>100</cost>
		<flags count_in_cargo="0" count_in_hoarder="0" count_in_map="1" count_in_player="0" crafted="0" deloot="0" />
		<category name="clothes" />
	</type>
	<type name="FB_SG_Jacket_pixel">
		<nominal>0</nominal>
		<lifetime>14400</lifetime>
		<restock>0</restock>
		<min>0</min>
		<quantmin>-1</quantmin>
		<quantmax>-1</quantmax>
		<cost>100</cost>
		<flags count_in_cargo="0" count_in_hoarder="0" count_in_map="1" count_in_player="0" crafted="0" deloot="0" />
		<category name="clothes" />
	</type>
	<type name="FB_SG_Jacket_black">
		<nominal>0</nominal>
		<lifetime>14400</lifetime>
		<restock>0</restock>
		<min>0</min>
		<quantmin>-1</quantmin>
		<quantmax>-1</quantmax>
		<cost>100</cost>
		<flags count_in_cargo="0" count_in_hoarder="0" count_in_map="1" count_in_player="0" crafted="0" deloot="0" />
		<category name="clothes" />
	</type>
	<type name="FB_SG_Jacket_green">
		<nominal>0</nominal>
		<lifetime>14400</lifetime>
		<restock>0</restock>
		<min>0</min>
		<quantmin>-1</quantmin>
		<quantmax>-1</quantmax>
		<cost>100</cost>
		<flags count_in_cargo="0" count_in_hoarder="0" count_in_map="1" count_in_player="0" crafted="0" deloot="0" />
		<category name="clothes" />
	</type>
	<type name="FB_SG_Gloves">
		<nominal>0</nominal>
		<lifetime>14400</lifetime>
		<restock>0</restock>
		<min>0</min>
		<quantmin>-1</quantmin>
		<quantmax>-1</quantmax>
		<cost>100</cost>
		<flags count_in_cargo="0" count_in_hoarder="0" count_in_map="1" count_in_player="0" crafted="0" deloot="0" />
		<category name="clothes" />
	</type>
	<type name="FB_SG_Boots">
		<nominal>0</nominal>
		<lifetime>14400</lifetime>
		<restock>0</restock>
		<min>0</min>
		<quantmin>-1</quantmin>
		<quantmax>-1</quantmax>
		<cost>100</cost>
		<flags count_in_cargo="0" count_in_hoarder="0" count_in_map="1" count_in_player="0" crafted="0" deloot="0" />
		<category name="clothes" />
	</type>
	<type name="FB_gorka_workwear">
		<nominal>0</nominal>
		<lifetime>14400</lifetime>
		<restock>0</restock>
		<min>0</min>
		<quantmin>-1</quantmin>
		<quantmax>-1</quantmax>
		<cost>100</cost>
		<flags count_in_cargo="0" count_in_hoarder="0" count_in_map="1" count_in_player="0" crafted="0" deloot="0" />
		<category name="clothes" />
	</type>
	<type name="FB_gorka_j_green">
		<nominal>0</nominal>
		<lifetime>14400</lifetime>
		<restock>0</restock>
		<min>0</min>
		<quantmin>-1</quantmin>
		<quantmax>-1</quantmax>
		<cost>100</cost>
		<flags count_in_cargo="0" count_in_hoarder="0" count_in_map="1" count_in_player="0" crafted="0" deloot="0" />
		<category name="clothes" />
	</type>
	<type name="FB_gorka_j_tan">
		<nominal>0</nominal>
		<lifetime>14400</lifetime>
		<restock>0</restock>
		<min>0</min>
		<quantmin>-1</quantmin>
		<quantmax>-1</quantmax>
		<cost>100</cost>
		<flags count_in_cargo="0" count_in_hoarder="0" count_in_map="1" count_in_player="0" crafted="0" deloot="0" />
		<category name="clothes" />
	</type>
	<type name="FB_rubashka_redneck_red">
		<nominal>15</nominal>
		<lifetime>14400</lifetime>
		<restock>0</restock>
		<min>10</min>
		<quantmin>-1</quantmin>
		<quantmax>-1</quantmax>
		<cost>100</cost>
		<flags count_in_cargo="0" count_in_hoarder="0" count_in_map="1" count_in_player="0" crafted="0" deloot="0" />
		<category name="clothes" />
		<usage name="Town" />
		<value name="Tier1" />
		<value name="Tier2" />
	</type>
	<type name="FB_rubashka_redneck_black">
		<nominal>15</nominal>
		<lifetime>14400</lifetime>
		<restock>0</restock>
		<min>10</min>
		<quantmin>-1</quantmin>
		<quantmax>-1</quantmax>
		<cost>100</cost>
		<flags count_in_cargo="0" count_in_hoarder="0" count_in_map="1" count_in_player="0" crafted="0" deloot="0" />
		<category name="clothes" />
		<usage name="Town" />
		<value name="Tier1" />
		<value name="Tier2" />
	</type>
	<type name="FB_rubashka_redneck_blue">
		<nominal>15</nominal>
		<lifetime>14400</lifetime>
		<restock>0</restock>
		<min>10</min>
		<quantmin>-1</quantmin>
		<quantmax>-1</quantmax>
		<cost>100</cost>
		<flags count_in_cargo="0" count_in_hoarder="0" count_in_map="1" count_in_player="0" crafted="0" deloot="0" />
		<category name="clothes" />
		<usage name="Town" />
		<value name="Tier1" />
		<value name="Tier2" />
	</type>
	<type name="FB_rubashka_redneck_green">
		<nominal>15</nominal>
		<lifetime>14400</lifetime>
		<restock>0</restock>
		<min>10</min>
		<quantmin>-1</quantmin>
		<quantmax>-1</quantmax>
		<cost>100</cost>
		<flags count_in_cargo="0" count_in_hoarder="0" count_in_map="1" count_in_player="0" crafted="0" deloot="0" />
		<category name="clothes" />
		<usage name="Town" />
		<value name="Tier1" />
		<value name="Tier2" />
	</type>
	<type name="FB_rubashka_redneck_green2">
		<nominal>15</nominal>
		<lifetime>14400</lifetime>
		<restock>0</restock>
		<min>10</min>
		<quantmin>-1</quantmin>
		<quantmax>-1</quantmax>
		<cost>100</cost>
		<flags count_in_cargo="0" count_in_hoarder="0" count_in_map="1" count_in_player="0" crafted="0" deloot="0" />
		<category name="clothes" />
		<usage name="Town" />
		<value name="Tier1" />
		<value name="Tier2" />
	</type>
	<type name="FB_rubashka_redneck_grey">
		<nominal>15</nominal>
		<lifetime>14400</lifetime>
		<restock>0</restock>
		<min>10</min>
		<quantmin>-1</quantmin>
		<quantmax>-1</quantmax>
		<cost>100</cost>
		<flags count_in_cargo="0" count_in_hoarder="0" count_in_map="1" count_in_player="0" crafted="0" deloot="0" />
		<category name="clothes" />
		<usage name="Town" />
		<value name="Tier1" />
		<value name="Tier2" />
	</type>
	<type name="FB_rubashka_redneck_mint">
		<nominal>15</nominal>
		<lifetime>14400</lifetime>
		<restock>0</restock>
		<min>10</min>
		<quantmin>-1</quantmin>
		<quantmax>-1</quantmax>
		<cost>100</cost>
		<flags count_in_cargo="0" count_in_hoarder="0" count_in_map="1" count_in_player="0" crafted="0" deloot="0" />
		<category name="clothes" />
		<usage name="Town" />
		<value name="Tier1" />
		<value name="Tier2" />
	</type>
	<type name="FB_rubashka2_white">
		<nominal>0</nominal>
		<lifetime>14400</lifetime>
		<restock>0</restock>
		<min>0</min>
		<quantmin>-1</quantmin>
		<quantmax>-1</quantmax>
		<cost>100</cost>
		<flags count_in_cargo="0" count_in_hoarder="0" count_in_map="1" count_in_player="0" crafted="0" deloot="0" />
		<category name="clothes" />
	</type>
	<type name="FB_rubashka2_white_bloody">
		<nominal>0</nominal>
		<lifetime>14400</lifetime>
		<restock>0</restock>
		<min>0</min>
		<quantmin>-1</quantmin>
		<quantmax>-1</quantmax>
		<cost>100</cost>
		<flags count_in_cargo="0" count_in_hoarder="0" count_in_map="1" count_in_player="0" crafted="0" deloot="0" />
		<category name="clothes" />
	</type>
	<type name="FB_stalker_sweater">
		<nominal>80</nominal>
		<lifetime>14400</lifetime>
		<restock>0</restock>
		<min>60</min>
		<quantmin>-1</quantmin>
		<quantmax>-1</quantmax>
		<cost>100</cost>
		<flags count_in_cargo="0" count_in_hoarder="0" count_in_map="1" count_in_player="0" crafted="0" deloot="0" />
		<category name="clothes" />
		<usage name="Town" />
		<usage name="Village" />
		<usage name="TrainCrash"/>
		<value name="Tier2" />
		<value name="Tier3" />
		<value name="Tier4" />
	</type>
	<type name="FB_tatical_jacket">
		<nominal>0</nominal>
		<lifetime>14400</lifetime>
		<restock>0</restock>
		<min>0</min>
		<quantmin>-1</quantmin>
		<quantmax>-1</quantmax>
		<cost>100</cost>
		<flags count_in_cargo="0" count_in_hoarder="0" count_in_map="1" count_in_player="0" crafted="0" deloot="0" />
		<category name="clothes" />
	</type>
	<type name="FB_tactical_jacket_black">
		<nominal>0</nominal>
		<lifetime>14400</lifetime>
		<restock>0</restock>
		<min>0</min>
		<quantmin>-1</quantmin>
		<quantmax>-1</quantmax>
		<cost>100</cost>
		<flags count_in_cargo="0" count_in_hoarder="0" count_in_map="1" count_in_player="0" crafted="0" deloot="0" />
		<category name="clothes" />
	</type>
	<type name="FB_tactical_jacket_grey">
		<nominal>0</nominal>
		<lifetime>14400</lifetime>
		<restock>0</restock>
		<min>0</min>
		<quantmin>-1</quantmin>
		<quantmax>-1</quantmax>
		<cost>100</cost>
		<flags count_in_cargo="0" count_in_hoarder="0" count_in_map="1" count_in_player="0" crafted="0" deloot="0" />
		<category name="clothes" />
	</type>
	<type name="FB_tactical_jacket_leather">
		<nominal>0</nominal>
		<lifetime>14400</lifetime>
		<restock>0</restock>
		<min>0</min>
		<quantmin>-1</quantmin>
		<quantmax>-1</quantmax>
		<cost>100</cost>
		<flags count_in_cargo="0" count_in_hoarder="0" count_in_map="1" count_in_player="0" crafted="0" deloot="0" />
		<category name="clothes" />
	</type>
	<type name="FB_tactical_jacket_tan">
		<nominal>0</nominal>
		<lifetime>14400</lifetime>
		<restock>0</restock>
		<min>0</min>
		<quantmin>-1</quantmin>
		<quantmax>-1</quantmax>
		<cost>100</cost>
		<flags count_in_cargo="0" count_in_hoarder="0" count_in_map="1" count_in_player="0" crafted="0" deloot="0" />
		<category name="clothes" />
	</type>
	<type name="FB_tactical_jacket_sand">
		<nominal>0</nominal>
		<lifetime>14400</lifetime>
		<restock>0</restock>
		<min>0</min>
		<quantmin>-1</quantmin>
		<quantmax>-1</quantmax>
		<cost>100</cost>
		<flags count_in_cargo="0" count_in_hoarder="0" count_in_map="1" count_in_player="0" crafted="0" deloot="0" />
		<category name="clothes" />
	</type>
	<type name="FB_tactical_jacket_green">
		<nominal>0</nominal>
		<lifetime>14400</lifetime>
		<restock>0</restock>
		<min>0</min>
		<quantmin>-1</quantmin>
		<quantmax>-1</quantmax>
		<cost>100</cost>
		<flags count_in_cargo="0" count_in_hoarder="0" count_in_map="1" count_in_player="0" crafted="0" deloot="0" />
		<category name="clothes" />
	</type>
	<type name="FB_vatnik_tan">
		<nominal>0</nominal>
		<lifetime>14400</lifetime>
		<restock>0</restock>
		<min>0</min>
		<quantmin>-1</quantmin>
		<quantmax>-1</quantmax>
		<cost>100</cost>
		<flags count_in_cargo="0" count_in_hoarder="0" count_in_map="1" count_in_player="0" crafted="0" deloot="0" />
		<category name="clothes" />
	</type>
	<type name="FB_vatnik_black">
		<nominal>0</nominal>
		<lifetime>14400</lifetime>
		<restock>0</restock>
		<min>0</min>
		<quantmin>-1</quantmin>
		<quantmax>-1</quantmax>
		<cost>100</cost>
		<flags count_in_cargo="0" count_in_hoarder="0" count_in_map="1" count_in_player="0" crafted="0" deloot="0" />
		<category name="clothes" />
	</type>
	<type name="FB_rubashka_red">
		<nominal>30</nominal>
		<lifetime>14400</lifetime>
		<restock>0</restock>
		<min>25</min>
		<quantmin>-1</quantmin>
		<quantmax>-1</quantmax>
		<cost>100</cost>
		<flags count_in_cargo="0" count_in_hoarder="0" count_in_map="1" count_in_player="0" crafted="0" deloot="0" />
		<category name="clothes" />
		<usage name="Town" />
		<usage name="Village" />
		<value name="Tier1" />
		<value name="Tier2" />
	</type>
	<type name="FB_rubashka_black">
		<nominal>30</nominal>
		<lifetime>14400</lifetime>
		<restock>0</restock>
		<min>25</min>
		<quantmin>-1</quantmin>
		<quantmax>-1</quantmax>
		<cost>100</cost>
		<flags count_in_cargo="0" count_in_hoarder="0" count_in_map="1" count_in_player="0" crafted="0" deloot="0" />
		<category name="clothes" />
		<usage name="Town" />
		<usage name="Village" />
		<usage name="TrainCrash"/>
		<value name="Tier1" />
		<value name="Tier2" />
	</type>
	<type name="FB_rubashka_green">
		<nominal>30</nominal>
		<lifetime>14400</lifetime>
		<restock>0</restock>
		<min>25</min>
		<quantmin>-1</quantmin>
		<quantmax>-1</quantmax>
		<cost>100</cost>
		<flags count_in_cargo="0" count_in_hoarder="0" count_in_map="1" count_in_player="0" crafted="0" deloot="0" />
		<category name="clothes" />
		<usage name="Town" />
		<usage name="Village" />
		<value name="Tier1" />
		<value name="Tier2" />
	</type>
	<type name="FB_rubashka_tan">
		<nominal>30</nominal>
		<lifetime>14400</lifetime>
		<restock>0</restock>
		<min>25</min>
		<quantmin>-1</quantmin>
		<quantmax>-1</quantmax>
		<cost>100</cost>
		<flags count_in_cargo="0" count_in_hoarder="0" count_in_map="1" count_in_player="0" crafted="0" deloot="0" />
		<category name="clothes" />
		<usage name="Town" />
		<usage name="Village" />
		<value name="Tier1" />
		<value name="Tier2" />
	</type>
	<type name="FB_kuguru_rainbow">
		<nominal>0</nominal>
		<lifetime>14400</lifetime>
		<restock>0</restock>
		<min>0</min>
		<quantmin>-1</quantmin>
		<quantmax>-1</quantmax>
		<cost>100</cost>
		<flags count_in_cargo="0" count_in_hoarder="0" count_in_map="1" count_in_player="0" crafted="0" deloot="0" />
		<category name="clothes" />
	</type>
	<type name="FB_kuguru_blue">
		<nominal>0</nominal>
		<lifetime>14400</lifetime>
		<restock>0</restock>
		<min>0</min>
		<quantmin>-1</quantmin>
		<quantmax>-1</quantmax>
		<cost>100</cost>
		<flags count_in_cargo="0" count_in_hoarder="0" count_in_map="1" count_in_player="0" crafted="0" deloot="0" />
		<category name="clothes" />
	</type>
	<type name="FB_kuguru_green">
		<nominal>0</nominal>
		<lifetime>14400</lifetime>
		<restock>0</restock>
		<min>0</min>
		<quantmin>-1</quantmin>
		<quantmax>-1</quantmax>
		<cost>100</cost>
		<flags count_in_cargo="0" count_in_hoarder="0" count_in_map="1" count_in_player="0" crafted="0" deloot="0" />
		<category name="clothes" />
	</type>
	<type name="FB_kuguru_red">
		<nominal>0</nominal>
		<lifetime>14400</lifetime>
		<restock>0</restock>
		<min>0</min>
		<quantmin>-1</quantmin>
		<quantmax>-1</quantmax>
		<cost>100</cost>
		<flags count_in_cargo="0" count_in_hoarder="0" count_in_map="1" count_in_player="0" crafted="0" deloot="0" />
		<category name="clothes" />
	</type>
	<type name="FB_kurtka_grey_brown">
		<nominal>50</nominal>
		<lifetime>14400</lifetime>
		<restock>0</restock>
		<min>40</min>
		<quantmin>-1</quantmin>
		<quantmax>-1</quantmax>
		<cost>100</cost>
		<flags count_in_cargo="0" count_in_hoarder="0" count_in_map="1" count_in_player="0" crafted="0" deloot="0" />
		<category name="clothes" />
		<usage name="Town" />
		<usage name="Village" />
		<usage name="TrainCrash"/>
		<value name="Tier1" />
		<value name="Tier2" />
	</type>
	<type name="FB_kurtka_black">
		<nominal>50</nominal>
		<lifetime>14400</lifetime>
		<restock>0</restock>
		<min>40</min>
		<quantmin>-1</quantmin>
		<quantmax>-1</quantmax>
		<cost>100</cost>
		<flags count_in_cargo="0" count_in_hoarder="0" count_in_map="1" count_in_player="0" crafted="0" deloot="0" />
		<category name="clothes" />
		<usage name="Town" />
		<usage name="Village" />
		<usage name="TrainCrash"/>
		<value name="Tier1" />
		<value name="Tier2" />
	</type>
	<type name="FB_kurtka_black_kish">
		<nominal>2</nominal>
		<lifetime>14400</lifetime>
		<restock>0</restock>
		<min>1</min>
		<quantmin>-1</quantmin>
		<quantmax>-1</quantmax>
		<cost>100</cost>
		<flags count_in_cargo="0" count_in_hoarder="0" count_in_map="1" count_in_player="0" crafted="0" deloot="0" />
		<category name="clothes" />
		<usage name="Town" />
		<usage name="Village" />
		<value name="Tier1" />
		<value name="Tier2" />
	</type>
	<type name="FB_kurtka_brown">
		<nominal>50</nominal>
		<lifetime>14400</lifetime>
		<restock>0</restock>
		<min>40</min>
		<quantmin>-1</quantmin>
		<quantmax>-1</quantmax>
		<cost>100</cost>
		<flags count_in_cargo="0" count_in_hoarder="0" count_in_map="1" count_in_player="0" crafted="0" deloot="0" />
		<category name="clothes" />
		<usage name="Town" />
		<usage name="Village" />
		<usage name="TrainCrash"/>
		<value name="Tier1" />
		<value name="Tier2" />
	</type>
	<type name="FB_plash_grey_brown">
		<nominal>0</nominal>
		<lifetime>14400</lifetime>
		<restock>0</restock>
		<min>0</min>
		<quantmin>-1</quantmin>
		<quantmax>-1</quantmax>
		<cost>100</cost>
		<flags count_in_cargo="0" count_in_hoarder="0" count_in_map="1" count_in_player="0" crafted="0" deloot="0" />
		<category name="clothes" />
	</type>
	<type name="FB_plash_black">
		<nominal>0</nominal>
		<lifetime>14400</lifetime>
		<restock>0</restock>
		<min>0</min>
		<quantmin>-1</quantmin>
		<quantmax>-1</quantmax>
		<cost>100</cost>
		<flags count_in_cargo="0" count_in_hoarder="0" count_in_map="1" count_in_player="0" crafted="0" deloot="0" />
		<category name="clothes" />
	</type>
	<type name="FB_plash_brown">
		<nominal>0</nominal>
		<lifetime>14400</lifetime>
		<restock>0</restock>
		<min>0</min>
		<quantmin>-1</quantmin>
		<quantmax>-1</quantmax>
		<cost>100</cost>
		<flags count_in_cargo="0" count_in_hoarder="0" count_in_map="1" count_in_player="0" crafted="0" deloot="0" />
		<category name="clothes" />
	</type>
	<type name="FB_bandit_yellow">
		<nominal>0</nominal>
		<lifetime>14400</lifetime>
		<restock>0</restock>
		<min>0</min>
		<quantmin>-1</quantmin>
		<quantmax>-1</quantmax>
		<cost>100</cost>
		<flags count_in_cargo="0" count_in_hoarder="0" count_in_map="1" count_in_player="0" crafted="0" deloot="0" />
		<category name="clothes" />
	</type>
	<type name="FB_bandit_yellow2">
		<nominal>0</nominal>
		<lifetime>14400</lifetime>
		<restock>0</restock>
		<min>0</min>
		<quantmin>-1</quantmin>
		<quantmax>-1</quantmax>
		<cost>100</cost>
		<flags count_in_cargo="0" count_in_hoarder="0" count_in_map="1" count_in_player="0" crafted="0" deloot="0" />
		<category name="clothes" />
	</type>
	<type name="FB_bandit_p_green">
		<nominal>0</nominal>
		<lifetime>14400</lifetime>
		<restock>0</restock>
		<min>0</min>
		<quantmin>-1</quantmin>
		<quantmax>-1</quantmax>
		<cost>100</cost>
		<flags count_in_cargo="0" count_in_hoarder="0" count_in_map="1" count_in_player="0" crafted="0" deloot="0" />
		<category name="clothes" />
	</type>
	<type name="FB_bandit_pants_black">
		<nominal>0</nominal>
		<lifetime>14400</lifetime>
		<restock>0</restock>
		<min>0</min>
		<quantmin>-1</quantmin>
		<quantmax>-1</quantmax>
		<cost>100</cost>
		<flags count_in_cargo="0" count_in_hoarder="0" count_in_map="1" count_in_player="0" crafted="0" deloot="0" />
		<category name="clothes" />
	</type>
	<type name="FB_bandit_pants_blue">
		<nominal>0</nominal>
		<lifetime>14400</lifetime>
		<restock>0</restock>
		<min>0</min>
		<quantmin>-1</quantmin>
		<quantmax>-1</quantmax>
		<cost>100</cost>
		<flags count_in_cargo="0" count_in_hoarder="0" count_in_map="1" count_in_player="0" crafted="0" deloot="0" />
		<category name="clothes" />
	</type>
	<type name="FB_bandit_pants_red">
		<nominal>0</nominal>
		<lifetime>14400</lifetime>
		<restock>0</restock>
		<min>0</min>
		<quantmin>-1</quantmin>
		<quantmax>-1</quantmax>
		<cost>100</cost>
		<flags count_in_cargo="0" count_in_hoarder="0" count_in_map="1" count_in_player="0" crafted="0" deloot="0" />
		<category name="clothes" />
	</type>
	<type name="FB_bandit_no_kneep_yellow">
		<nominal>0</nominal>
		<lifetime>14400</lifetime>
		<restock>0</restock>
		<min>0</min>
		<quantmin>-1</quantmin>
		<quantmax>-1</quantmax>
		<cost>100</cost>
		<flags count_in_cargo="0" count_in_hoarder="0" count_in_map="1" count_in_player="0" crafted="0" deloot="0" />
		<category name="clothes" />
	</type>
	<type name="FB_bandit_p_no_kneep_green">
		<nominal>0</nominal>
		<lifetime>14400</lifetime>
		<restock>0</restock>
		<min>0</min>
		<quantmin>-1</quantmin>
		<quantmax>-1</quantmax>
		<cost>100</cost>
		<flags count_in_cargo="0" count_in_hoarder="0" count_in_map="1" count_in_player="0" crafted="0" deloot="0" />
		<category name="clothes" />
	</type>
	<type name="FB_bandit_pants_no_kneep_black">
		<nominal>30</nominal>
		<lifetime>14400</lifetime>
		<restock>0</restock>
		<min>20</min>
		<quantmin>-1</quantmin>
		<quantmax>-1</quantmax>
		<cost>100</cost>
		<flags count_in_cargo="0" count_in_hoarder="0" count_in_map="1" count_in_player="0" crafted="0" deloot="0" />
		<category name="clothes" />
		<usage name="Town" />
		<value name="Tier1" />
		<value name="Tier2" />
	</type>
	<type name="FB_bandit_pants_no_kneep_blue">
		<nominal>30</nominal>
		<lifetime>14400</lifetime>
		<restock>0</restock>
		<min>20</min>
		<quantmin>-1</quantmin>
		<quantmax>-1</quantmax>
		<cost>100</cost>
		<flags count_in_cargo="0" count_in_hoarder="0" count_in_map="1" count_in_player="0" crafted="0" deloot="0" />
		<category name="clothes" />
		<usage name="Town" />
		<value name="Tier1" />
		<value name="Tier2" />
	</type>
	<type name="FB_bandit_pants_no_kneep_red">
		<nominal>30</nominal>
		<lifetime>14400</lifetime>
		<restock>0</restock>
		<min>20</min>
		<quantmin>-1</quantmin>
		<quantmax>-1</quantmax>
		<cost>100</cost>
		<flags count_in_cargo="0" count_in_hoarder="0" count_in_map="1" count_in_player="0" crafted="0" deloot="0" />
		<category name="clothes" />
		<usage name="Town" />
		<value name="Tier1" />
		<value name="Tier2" />
	</type>
	<type name="FB_HuntingPants_camo">
		<nominal>0</nominal>
		<lifetime>14400</lifetime>
		<restock>0</restock>
		<min>0</min>
		<quantmin>-1</quantmin>
		<quantmax>-1</quantmax>
		<cost>100</cost>
		<flags count_in_cargo="0" count_in_hoarder="0" count_in_map="1" count_in_player="0" crafted="0" deloot="0" />
		<category name="clothes" />
	</type>
	<type name="FB_HuntingPants_Blue">
		<nominal>0</nominal>
		<lifetime>14400</lifetime>
		<restock>0</restock>
		<min>0</min>
		<quantmin>-1</quantmin>
		<quantmax>-1</quantmax>
		<cost>100</cost>
		<flags count_in_cargo="0" count_in_hoarder="0" count_in_map="1" count_in_player="0" crafted="0" deloot="0" />
		<category name="clothes" />
	</type>
	<type name="FB_HuntingPants_Gray">
		<nominal>0</nominal>
		<lifetime>14400</lifetime>
		<restock>0</restock>
		<min>0</min>
		<quantmin>-1</quantmin>
		<quantmax>-1</quantmax>
		<cost>100</cost>
		<flags count_in_cargo="0" count_in_hoarder="0" count_in_map="1" count_in_player="0" crafted="0" deloot="0" />
		<category name="clothes" />
	</type>
	<type name="FB_HuntingPants_Green">
		<nominal>0</nominal>
		<lifetime>14400</lifetime>
		<restock>0</restock>
		<min>0</min>
		<quantmin>-1</quantmin>
		<quantmax>-1</quantmax>
		<cost>100</cost>
		<flags count_in_cargo="0" count_in_hoarder="0" count_in_map="1" count_in_player="0" crafted="0" deloot="0" />
		<category name="clothes" />
	</type>
	<type name="FB_HuntingJacket_blue">
		<nominal>0</nominal>
		<lifetime>14400</lifetime>
		<restock>0</restock>
		<min>0</min>
		<quantmin>-1</quantmin>
		<quantmax>-1</quantmax>
		<cost>100</cost>
		<flags count_in_cargo="0" count_in_hoarder="0" count_in_map="1" count_in_player="0" crafted="0" deloot="0" />
		<category name="clothes" />
	</type>
	<type name="FB_HuntingJacket_green">
		<nominal>0</nominal>
		<lifetime>14400</lifetime>
		<restock>0</restock>
		<min>0</min>
		<quantmin>-1</quantmin>
		<quantmax>-1</quantmax>
		<cost>100</cost>
		<flags count_in_cargo="0" count_in_hoarder="0" count_in_map="1" count_in_player="0" crafted="0" deloot="0" />
		<category name="clothes" />
	</type>
	<type name="FB_HuntingJacket_grey">
		<nominal>0</nominal>
		<lifetime>14400</lifetime>
		<restock>0</restock>
		<min>0</min>
		<quantmin>-1</quantmin>
		<quantmax>-1</quantmax>
		<cost>100</cost>
		<flags count_in_cargo="0" count_in_hoarder="0" count_in_map="1" count_in_player="0" crafted="0" deloot="0" />
		<category name="clothes" />
	</type>
	<type name="FB_HuntingJacket_brown">
		<nominal>0</nominal>
		<lifetime>14400</lifetime>
		<restock>0</restock>
		<min>0</min>
		<quantmin>-1</quantmin>
		<quantmax>-1</quantmax>
		<cost>100</cost>
		<flags count_in_cargo="0" count_in_hoarder="0" count_in_map="1" count_in_player="0" crafted="0" deloot="0" />
		<category name="clothes" />
	</type>
	<type name="FB_HuntingJacket_velveteen">
		<nominal>0</nominal>
		<lifetime>14400</lifetime>
		<restock>0</restock>
		<min>0</min>
		<quantmin>-1</quantmin>
		<quantmax>-1</quantmax>
		<cost>100</cost>
		<flags count_in_cargo="0" count_in_hoarder="0" count_in_map="1" count_in_player="0" crafted="0" deloot="0" />
		<category name="clothes" />
	</type>
	<type name="FB_HuntingJacket_camo">
		<nominal>0</nominal>
		<lifetime>14400</lifetime>
		<restock>0</restock>
		<min>0</min>
		<quantmin>-1</quantmin>
		<quantmax>-1</quantmax>
		<cost>100</cost>
		<flags count_in_cargo="0" count_in_hoarder="0" count_in_map="1" count_in_player="0" crafted="0" deloot="0" />
		<category name="clothes" />
	</type>
	<type name="FB_HuntingJacket_red">
		<nominal>0</nominal>
		<lifetime>14400</lifetime>
		<restock>0</restock>
		<min>0</min>
		<quantmin>-1</quantmin>
		<quantmax>-1</quantmax>
		<cost>100</cost>
		<flags count_in_cargo="0" count_in_hoarder="0" count_in_map="1" count_in_player="0" crafted="0" deloot="0" />
		<category name="clothes" />
	</type>
	<type name="FB_HuntingJacket_quilted">
		<nominal>0</nominal>
		<lifetime>14400</lifetime>
		<restock>0</restock>
		<min>0</min>
		<quantmin>-1</quantmin>
		<quantmax>-1</quantmax>
		<cost>100</cost>
		<flags count_in_cargo="0" count_in_hoarder="0" count_in_map="1" count_in_player="0" crafted="0" deloot="0" />
		<category name="clothes" />
	</type>
	<type name="FB_retro_pants_black">
		<nominal>30</nominal>
		<lifetime>14400</lifetime>
		<restock>0</restock>
		<min>25</min>
		<quantmin>-1</quantmin>
		<quantmax>-1</quantmax>
		<cost>100</cost>
		<flags count_in_cargo="0" count_in_hoarder="0" count_in_map="1" count_in_player="0" crafted="0" deloot="0" />
		<category name="clothes" />
		<usage name="Town" />
		<usage name="Village" />
		<value name="Tier1" />
	</type>
	<type name="FB_retro_pants_red">
		<nominal>30</nominal>
		<lifetime>14400</lifetime>
		<restock>0</restock>
		<min>25</min>
		<quantmin>-1</quantmin>
		<quantmax>-1</quantmax>
		<cost>100</cost>
		<flags count_in_cargo="0" count_in_hoarder="0" count_in_map="1" count_in_player="0" crafted="0" deloot="0" />
		<category name="clothes" />
		<usage name="Town" />
		<usage name="Village" />
		<value name="Tier1" />
	</type>
	<type name="FB_retro_pants_pink">
		<nominal>30</nominal>
		<lifetime>14400</lifetime>
		<restock>0</restock>
		<min>25</min>
		<quantmin>-1</quantmin>
		<quantmax>-1</quantmax>
		<cost>100</cost>
		<flags count_in_cargo="0" count_in_hoarder="0" count_in_map="1" count_in_player="0" crafted="0" deloot="0" />
		<category name="clothes" />
		<usage name="Town" />
		<usage name="Village" />
		<value name="Tier1" />
	</type>
	<type name="FB_shirt_walking_dead">
		<nominal>0</nominal>
		<lifetime>14400</lifetime>
		<restock>0</restock>
		<min>0</min>
		<quantmin>-1</quantmin>
		<quantmax>-1</quantmax>
		<cost>100</cost>
		<flags count_in_cargo="0" count_in_hoarder="0" count_in_map="1" count_in_player="0" crafted="0" deloot="0" />
		<category name="clothes" />
	</type>
	<type name="FB_TelnyashkaShirt_blue">
		<nominal>10</nominal>
		<lifetime>14400</lifetime>
		<restock>0</restock>
		<min>8</min>
		<quantmin>-1</quantmin>
		<quantmax>-1</quantmax>
		<cost>100</cost>
		<flags count_in_cargo="0" count_in_hoarder="0" count_in_map="1" count_in_player="0" crafted="0" deloot="0" />
		<category name="clothes" />
		<usage name="Town" />
		<usage name="Village" />
	</type>
	<type name="FB_TelnyashkaShirt_red">
		<nominal>10</nominal>
		<lifetime>14400</lifetime>
		<restock>0</restock>
		<min>8</min>
		<quantmin>-1</quantmin>
		<quantmax>-1</quantmax>
		<cost>100</cost>
		<flags count_in_cargo="0" count_in_hoarder="0" count_in_map="1" count_in_player="0" crafted="0" deloot="0" />
		<category name="clothes" />
		<usage name="Town" />
		<usage name="Village" />
	</type>
	<type name="FB_TelnyashkaShirt_green">
		<nominal>10</nominal>
		<lifetime>14400</lifetime>
		<restock>0</restock>
		<min>8</min>
		<quantmin>-1</quantmin>
		<quantmax>-1</quantmax>
		<cost>100</cost>
		<flags count_in_cargo="0" count_in_hoarder="0" count_in_map="1" count_in_player="0" crafted="0" deloot="0" />
		<category name="clothes" />
		<usage name="Town" />
		<usage name="Village" />
	</type>
	<type name="FB_retro_jacket_purple">
		<nominal>40</nominal>
		<lifetime>14400</lifetime>
		<restock>0</restock>
		<min>25</min>
		<quantmin>-1</quantmin>
		<quantmax>-1</quantmax>
		<cost>100</cost>
		<flags count_in_cargo="0" count_in_hoarder="0" count_in_map="1" count_in_player="0" crafted="0" deloot="0" />
		<category name="clothes" />
		<usage name="Town" />
		<usage name="Village" />
		<value name="Tier2" />
		<value name="Tier3" />
	</type>
	<type name="FB_retro_jacket_red">
		<nominal>40</nominal>
		<lifetime>14400</lifetime>
		<restock>0</restock>
		<min>25</min>
		<quantmin>-1</quantmin>
		<quantmax>-1</quantmax>
		<cost>100</cost>
		<flags count_in_cargo="0" count_in_hoarder="0" count_in_map="1" count_in_player="0" crafted="0" deloot="0" />
		<category name="clothes" />
		<usage name="Town" />
		<usage name="Village" />
		<value name="Tier2" />
		<value name="Tier3" />
	</type>
	<type name="FB_retro_jacket_pink">
		<nominal>40</nominal>
		<lifetime>14400</lifetime>
		<restock>0</restock>
		<min>25</min>
		<quantmin>-1</quantmin>
		<quantmax>-1</quantmax>
		<cost>100</cost>
		<flags count_in_cargo="0" count_in_hoarder="0" count_in_map="1" count_in_player="0" crafted="0" deloot="0" />
		<category name="clothes" />
		<usage name="Town" />
		<usage name="Village" />
		<value name="Tier2" />
		<value name="Tier3" />
	</type>
	<type name="FB_half_gloves_blue">
		<nominal>0</nominal>
		<lifetime>14400</lifetime>
		<restock>0</restock>
		<min>0</min>
		<quantmin>-1</quantmin>
		<quantmax>-1</quantmax>
		<cost>100</cost>
		<flags count_in_cargo="0" count_in_hoarder="0" count_in_map="1" count_in_player="0" crafted="0" deloot="0" />
		<category name="clothes" />
	</type>
	<type name="FB_half_gloves_green">
		<nominal>0</nominal>
		<lifetime>14400</lifetime>
		<restock>0</restock>
		<min>0</min>
		<quantmin>-1</quantmin>
		<quantmax>-1</quantmax>
		<cost>100</cost>
		<flags count_in_cargo="0" count_in_hoarder="0" count_in_map="1" count_in_player="0" crafted="0" deloot="0" />
		<category name="clothes" />
	</type>
	<type name="FB_half_gloves_grey">
		<nominal>0</nominal>
		<lifetime>14400</lifetime>
		<restock>0</restock>
		<min>0</min>
		<quantmin>-1</quantmin>
		<quantmax>-1</quantmax>
		<cost>100</cost>
		<flags count_in_cargo="0" count_in_hoarder="0" count_in_map="1" count_in_player="0" crafted="0" deloot="0" />
		<category name="clothes" />
	</type>
	<type name="FB_half_gloves_black">
		<nominal>0</nominal>
		<lifetime>14400</lifetime>
		<restock>0</restock>
		<min>0</min>
		<quantmin>-1</quantmin>
		<quantmax>-1</quantmax>
		<cost>100</cost>
		<flags count_in_cargo="0" count_in_hoarder="0" count_in_map="1" count_in_player="0" crafted="0" deloot="0" />
		<category name="clothes" />
	</type>
	<type name="FB_half_gloves_red">
		<nominal>0</nominal>
		<lifetime>14400</lifetime>
		<restock>0</restock>
		<min>0</min>
		<quantmin>-1</quantmin>
		<quantmax>-1</quantmax>
		<cost>100</cost>
		<flags count_in_cargo="0" count_in_hoarder="0" count_in_map="1" count_in_player="0" crafted="0" deloot="0" />
		<category name="clothes" />
	</type>
	<type name="FB_Beanie_cap_2_black">
		<nominal>25</nominal>
		<lifetime>14400</lifetime>
		<restock>0</restock>
		<min>15</min>
		<quantmin>-1</quantmin>
		<quantmax>-1</quantmax>
		<cost>100</cost>
		<flags count_in_cargo="0" count_in_hoarder="0" count_in_map="1" count_in_player="0" crafted="0" deloot="0" />
		<category name="clothes" />
		<tag name="shelves" />
		<usage name="Town"/>
		<usage name="Village"/>
	</type>
	<type name="FB_Beanie_cap_2_blue">
		<nominal>25</nominal>
		<lifetime>14400</lifetime>
		<restock>0</restock>
		<min>15</min>
		<quantmin>-1</quantmin>
		<quantmax>-1</quantmax>
		<cost>100</cost>
		<flags count_in_cargo="0" count_in_hoarder="0" count_in_map="1" count_in_player="0" crafted="0" deloot="0" />
		<category name="clothes" />
		<tag name="shelves" />
		<usage name="Town"/>
		<usage name="Village"/>
	</type>
	<type name="FB_Beanie_cap_2_green">
		<nominal>25</nominal>
		<lifetime>14400</lifetime>
		<restock>0</restock>
		<min>15</min>
		<quantmin>-1</quantmin>
		<quantmax>-1</quantmax>
		<cost>100</cost>
		<flags count_in_cargo="0" count_in_hoarder="0" count_in_map="1" count_in_player="0" crafted="0" deloot="0" />
		<category name="clothes" />
		<tag name="shelves" />
		<usage name="Town"/>
		<usage name="Village"/>
		<usage name="TrainCrash"/>
	</type>
	<type name="FB_Beanie_cap_2_grey">
		<nominal>25</nominal>
		<lifetime>14400</lifetime>
		<restock>0</restock>
		<min>15</min>
		<quantmin>-1</quantmin>
		<quantmax>-1</quantmax>
		<cost>100</cost>
		<flags count_in_cargo="0" count_in_hoarder="0" count_in_map="1" count_in_player="0" crafted="0" deloot="0" />
		<category name="clothes" />
		<tag name="shelves" />
		<usage name="Town"/>
		<usage name="Village"/>
		<usage name="TrainCrash"/>
	</type>
	<type name="FB_Beanie_cap_2_yellow">
		<nominal>25</nominal>
		<lifetime>14400</lifetime>
		<restock>0</restock>
		<min>15</min>
		<quantmin>-1</quantmin>
		<quantmax>-1</quantmax>
		<cost>100</cost>
		<flags count_in_cargo="0" count_in_hoarder="0" count_in_map="1" count_in_player="0" crafted="0" deloot="0" />
		<category name="clothes" />
		<tag name="shelves" />
		<usage name="Town"/>
		<usage name="Village"/>
		<usage name="TrainCrash"/>
	</type>
	<type name="VM_Leather_bag_25">
		<nominal>0</nominal>
		<lifetime>7200</lifetime>
		<restock>0</restock>
		<min>0</min>
		<quantmin>-1</quantmin>
		<quantmax>-1</quantmax>
		<cost>100</cost>
		<flags count_in_cargo="0" count_in_hoarder="0" count_in_map="1" count_in_player="0" crafted="0" deloot="0"/>
	</type>
	<type name="VM_Leather_bag_35">
		<nominal>0</nominal>
		<lifetime>7200</lifetime>
		<restock>0</restock>
		<min>0</min>
		<quantmin>-1</quantmin>
		<quantmax>-1</quantmax>
		<cost>100</cost>
		<flags count_in_cargo="0" count_in_hoarder="0" count_in_map="1" count_in_player="0" crafted="0" deloot="0"/>
	</type>
	<type name="VM_Leather_bag_45">
		<nominal>0</nominal>
		<lifetime>7200</lifetime>
		<restock>0</restock>
		<min>0</min>
		<quantmin>-1</quantmin>
		<quantmax>-1</quantmax>
		<cost>100</cost>
		<flags count_in_cargo="0" count_in_hoarder="0" count_in_map="1" count_in_player="0" crafted="0" deloot="0"/>
	</type>
	<type name="VM_Leather_bag_60">
		<nominal>0</nominal>
		<lifetime>7200</lifetime>
		<restock>0</restock>
		<min>0</min>
		<quantmin>-1</quantmin>
		<quantmax>-1</quantmax>
		<cost>100</cost>
		<flags count_in_cargo="0" count_in_hoarder="0" count_in_map="1" count_in_player="0" crafted="0" deloot="0"/>
	</type>
	<type name="VM_Leather_bag_80">
		<nominal>0</nominal>
		<lifetime>7200</lifetime>
		<restock>0</restock>
		<min>0</min>
		<quantmin>-1</quantmin>
		<quantmax>-1</quantmax>
		<cost>100</cost>
		<flags count_in_cargo="0" count_in_hoarder="0" count_in_map="1" count_in_player="0" crafted="0" deloot="0"/>
	</type>
	<type name="VM_Leather_bag_100">
		<nominal>0</nominal>
		<lifetime>7200</lifetime>
		<restock>0</restock>
		<min>0</min>
		<quantmin>-1</quantmin>
		<quantmax>-1</quantmax>
		<cost>100</cost>
		<flags count_in_cargo="0" count_in_hoarder="0" count_in_map="1" count_in_player="0" crafted="0" deloot="0"/>
	</type>
	<type name="VM_Leather_bag_120">
		<nominal>0</nominal>
		<lifetime>7200</lifetime>
		<restock>0</restock>
		<min>0</min>
		<quantmin>-1</quantmin>
		<quantmax>-1</quantmax>
		<cost>100</cost>
		<flags count_in_cargo="0" count_in_hoarder="0" count_in_map="1" count_in_player="0" crafted="0" deloot="0"/>
	</type>
	<type name="VM_Leather_bag_140">
		<nominal>0</nominal>
		<lifetime>7200</lifetime>
		<restock>0</restock>
		<min>0</min>
		<quantmin>-1</quantmin>
		<quantmax>-1</quantmax>
		<cost>100</cost>
		<flags count_in_cargo="0" count_in_hoarder="0" count_in_map="1" count_in_player="0" crafted="0" deloot="0"/>
	</type>
	<type name="VM_Leather_bag_160">
		<nominal>0</nominal>
		<lifetime>7200</lifetime>
		<restock>0</restock>
		<min>0</min>
		<quantmin>-1</quantmin>
		<quantmax>-1</quantmax>
		<cost>100</cost>
		<flags count_in_cargo="0" count_in_hoarder="0" count_in_map="1" count_in_player="0" crafted="0" deloot="0"/>
	</type>
</types>